[
  {
    "flightNumber": "17274",
    "originIATA": "POA",
    "destinationIATA": "DFW",
    "airline": "LATAM",
    "aircraftID": "7FB013092SJD24667"
  },
  {
    "flightNumber": "36458",
    "originIATA": "TUN",
    "destinationIATA": "DME",
    "airline": "Qatar",
    "aircraftID": "RSV1ZPBJ1BPH94145"
  },
  {
    "flightNumber": "75301",
    "originIATA": "LST",
    "destinationIATA": "DUB",
    "airline": "LATAM",
    "aircraftID": "L5SP9GLK1KNJ51457"
  },
  {
    "flightNumber": "84039",
    "originIATA": "BOG",
    "destinationIATA": "MIR",
    "airline": "LATAM",
    "aircraftID": "6ZW9F5EZK7VT26121"
  },
  {
    "flightNumber": "96706",
    "originIATA": "DUB",
    "destinationIATA": "VCP",
    "airline": "LATAM",
    "aircraftID": "YW4BJ4T0G6B317989"
  },
  {
    "flightNumber": "71762",
    "originIATA": "LAS",
    "destinationIATA": "LST",
    "airline": "Qatar",
    "aircraftID": "XU1EK2604GHV21166"
  },
  {
    "flightNumber": "27692",
    "originIATA": "KRT",
    "destinationIATA": "TPE",
    "airline": "British Airways",
    "aircraftID": "P0GD7Z5B12DH89719"
  },
  {
    "flightNumber": "37801",
    "originIATA": "KMG",
    "destinationIATA": "TIJ",
    "airline": "Qatar",
    "aircraftID": "KFM7YJPG7YMV14074"
  },
  {
    "flightNumber": "20044",
    "originIATA": "BWI",
    "destinationIATA": "SVO",
    "airline": "British Airways",
    "aircraftID": "92BJS9V3TJJG65093"
  },
  {
    "flightNumber": "10372",
    "originIATA": "ROK",
    "destinationIATA": "BCN",
    "airline": "British Airways",
    "aircraftID": "US68AML12VTY94285"
  },
  {
    "flightNumber": "96947",
    "originIATA": "LGW",
    "destinationIATA": "TSV",
    "airline": "Emirates",
    "aircraftID": "E1B9S4KWT4DN18647"
  },
  {
    "flightNumber": "70260",
    "originIATA": "DRW",
    "destinationIATA": "MSP",
    "airline": "LATAM",
    "aircraftID": "UAWKNLV0AXDV26391"
  },
  {
    "flightNumber": "16474",
    "originIATA": "SLC",
    "destinationIATA": "SAW",
    "airline": "Iberia",
    "aircraftID": "CET2AF666JRJ19933"
  },
  {
    "flightNumber": "27696",
    "originIATA": "HRG",
    "destinationIATA": "DUS",
    "airline": "British Airways",
    "aircraftID": "RFPUNRCPBHJN75137"
  },
  {
    "flightNumber": "40985",
    "originIATA": "CPT",
    "destinationIATA": "VCP",
    "airline": "American",
    "aircraftID": "H0H0E0KDMDW788322"
  },
  {
    "flightNumber": "15015",
    "originIATA": "PER",
    "destinationIATA": "SLC",
    "airline": "British Airways",
    "aircraftID": "P6XUP7DBNJU985251"
  },
  {
    "flightNumber": "86014",
    "originIATA": "RAK",
    "destinationIATA": "MTY",
    "airline": "Qatar",
    "aircraftID": "0M7HCSPA8REM15345"
  },
  {
    "flightNumber": "53778",
    "originIATA": "MKY",
    "destinationIATA": "POM",
    "airline": "Qatar",
    "aircraftID": "32NHVUBBL4YC35083"
  },
  {
    "flightNumber": "68024",
    "originIATA": "DTW",
    "destinationIATA": "HTI",
    "airline": "British Airways",
    "aircraftID": "G9BS3702Y8EP21611"
  },
  {
    "flightNumber": "32602",
    "originIATA": "KUL",
    "destinationIATA": "WLG",
    "airline": "Qatar",
    "aircraftID": "800C2N1NFFU486626"
  },
  {
    "flightNumber": "72253",
    "originIATA": "HND",
    "destinationIATA": "CPT",
    "airline": "LATAM",
    "aircraftID": "FMNGUTMJPJF181400"
  },
  {
    "flightNumber": "95182",
    "originIATA": "HRG",
    "destinationIATA": "KUL",
    "airline": "American",
    "aircraftID": "4HTWMJBYEKS130491"
  },
  {
    "flightNumber": "68623",
    "originIATA": "HBE",
    "destinationIATA": "BRU",
    "airline": "American",
    "aircraftID": "UPJDCWY56PUV72433"
  },
  {
    "flightNumber": "99306",
    "originIATA": "BWI",
    "destinationIATA": "ORD",
    "airline": "Emirates",
    "aircraftID": "3HADP3KD8KP827744"
  },
  {
    "flightNumber": "75424",
    "originIATA": "HGH",
    "destinationIATA": "DUB",
    "airline": "LATAM",
    "aircraftID": "9C730ZV26FJB91841"
  },
  {
    "flightNumber": "94216",
    "originIATA": "CGK",
    "destinationIATA": "VIE",
    "airline": "Qatar",
    "aircraftID": "A6C5JX64PXFB32163"
  },
  {
    "flightNumber": "18397",
    "originIATA": "CJU",
    "destinationIATA": "FOR",
    "airline": "British Airways",
    "aircraftID": "AZV3XJYARTN661156"
  },
  {
    "flightNumber": "17615",
    "originIATA": "LIM",
    "destinationIATA": "CAI",
    "airline": "Qatar",
    "aircraftID": "WHW6VUBPGKH015366"
  },
  {
    "flightNumber": "79864",
    "originIATA": "GDL",
    "destinationIATA": "HAV",
    "airline": "LATAM",
    "aircraftID": "NFD3EM0LF8G766399"
  },
  {
    "flightNumber": "48364",
    "originIATA": "DFW",
    "destinationIATA": "CPT",
    "airline": "Qatar",
    "aircraftID": "F0GPJX73WZCU76526"
  }
]